devopstemplate/__init__.py
devopstemplate/commands.json
devopstemplate/config.py
devopstemplate/log.py
devopstemplate/main.py
devopstemplate/makefile.py
devopstemplate/pkg.py
devopstemplate/template.json
devopstemplate/template.py
devopstemplate/template/.dockerignore
devopstemplate/template/.gitignore
devopstemplate/template/.sonartoken
devopstemplate/template/Dockerfile
devopstemplate/template/MANIFEST.in
devopstemplate/template/Makefile
devopstemplate/template/README.md
devopstemplate/template/entrypoint.sh
devopstemplate/template/requirements.txt
devopstemplate/template/setup.mk
devopstemplate/template/setup.py
devopstemplate/template/mlflow/README.md
devopstemplate/template/mlflow/docker-compose.yml
devopstemplate/template/mlflow/mlflow_sample.py
devopstemplate/template/mongodb/README.md
devopstemplate/template/mongodb/docker-compose.yml
devopstemplate/template/mongodb/mongo_sample.py
devopstemplate/template/sonarqube/README.md
devopstemplate/template/sonarqube/docker-compose.yml
devopstemplate/template/tests/test_{{project_slug}}.py
devopstemplate/template/{{project_slug}}/__init__.py
devopstemplate/template/{{project_slug}}/log.py
devopstemplate/template/{{project_slug}}/main.py
devopstemplate-0.9.0.dist-info/LICENSE
devopstemplate-0.9.0.dist-info/METADATA
devopstemplate-0.9.0.dist-info/WHEEL
devopstemplate-0.9.0.dist-info/entry_points.txt
devopstemplate-0.9.0.dist-info/top_level.txt
devopstemplate-0.9.0.dist-info/RECORD
