Metadata-Version: 2.1
Name: devopstemplate
Version: 0.9.0
Summary: This package provides a command-line interface for setting up a Python project based on a dev-ops template
Home-page: https://github.com/lrothack/dev-ops-admin
Author: Leonard Rothacker
Author-email: leonard.rothacker@googlemail.com
License: MIT
Keywords: devops template sonarqube docker code-analysis
Platform: any
Classifier: Intended Audience :: Developers
Classifier: License :: OSI Approved :: MIT License
Classifier: Programming Language :: Python :: 3.6
Classifier: Programming Language :: Python :: 3.7
Classifier: Programming Language :: Python :: 3.8
Classifier: Programming Language :: Python :: 3.9
Classifier: Environment :: Console
Requires-Python: >= 3.6
License-File: LICENSE
Requires-Dist: Jinja2
Provides-Extra: dev
Requires-Dist: pip (>=20.1.1) ; extra == 'dev'
Requires-Dist: wheel ; extra == 'dev'
Requires-Dist: pytest ; extra == 'dev'
Requires-Dist: coverage ; extra == 'dev'
Requires-Dist: bandit ; extra == 'dev'
Requires-Dist: pylint ; extra == 'dev'
Requires-Dist: autopep8 ; extra == 'dev'
Requires-Dist: flake8 ; extra == 'dev'
